[
  { "name": "Basmati Rice", "main": "Food", "sub": "Grains", "type": "Rice", "price": 1200, "image": "images/rice.jpg" },
  { "name": "Brown Rice", "main": "Food", "sub": "Grains", "type": "Rice", "price": 900, "image": "images/rice.jpg" },
  { "name": "Wheat Flour", "main": "Food", "sub": "Grains", "type": "Flour", "price": 80, "image": "images/wheat_flour.jpg" },
  { "name": "Sunflower Oil", "main": "Food", "sub": "Oil", "type": "Refined Oil", "price": 300, "image": "images/sunflower_oil.jpg" },
  { "name": "Mustard Oil", "main": "Food", "sub": "Oil", "type": "Cold Pressed", "price": 350, "image": "images/mustard_oil.jpg" },
  { "name": "Sugar", "main": "Food", "sub": "Sweeteners", "type": "Sugar", "price": 150, "image": "images/sugar.jpg" },
  { "name": "Salt", "main": "Food", "sub": "Spices", "type": "Table Salt", "price": 50, "image": "images/salt.jpg" },
  { "name": "Black Pepper", "main": "Food", "sub": "Spices", "type": "Whole", "price": 120, "image": "images/black_pepper.jpg" },
  { "name": "Chili Powder", "main": "Food", "sub": "Spices", "type": "Powder", "price": 100, "image": "images/chili_powder.jpg" },
  { "name": "Cumin Seeds", "main": "Food", "sub": "Spices", "type": "Seeds", "price": 90, "image": "images/cumin_seeds.jpg" },
  { "name": "Red Lentils", "main": "Food", "sub": "Pulses", "type": "Lentils", "price": 200, "image": "images/red_lentils.jpg" },
  { "name": "Green Lentils", "main": "Food", "sub": "Pulses", "type": "Lentils", "price": 180, "image": "images/green_lentils.jpg" },
  { "name": "Chickpeas", "main": "Food", "sub": "Pulses", "type": "Chana", "price": 220, "image": "images/chickpeas.jpg" },
  { "name": "Kidney Beans", "main": "Food", "sub": "Pulses", "type": "Beans", "price": 250, "image": "images/kidney_beans.jpg" },
  { "name": "Soybeans", "main": "Food", "sub": "Pulses", "type": "Beans", "price": 300, "image": "images/soybeans.jpg" },
  { "name": "Apple", "main": "Food", "sub": "Fruits", "type": "Red", "price": 120, "image": "images/apple.jpg" },
  { "name": "Banana", "main": "Food", "sub": "Fruits", "type": "Yellow", "price": 50, "image": "images/banana.jpg" },
  { "name": "Mango", "main": "Food", "sub": "Fruits", "type": "Tropical", "price": 200, "image": "images/mango.jpg" },
  { "name": "Orange", "main": "Food", "sub": "Fruits", "type": "Citrus", "price": 90, "image": "images/orange.jpg" },
  { "name": "Grapes", "main": "Food", "sub": "Fruits", "type": "Green", "price": 150, "image": "images/grapes.jpg" },
  { "name": "Carrot", "main": "Food", "sub": "Vegetables", "type": "Root", "price": 60, "image": "images/carrot.jpg" },
  { "name": "Potato", "main": "Food", "sub": "Vegetables", "type": "Root", "price": 40, "image": "images/potato.jpg" },
  { "name": "Tomato", "main": "Food", "sub": "Vegetables", "type": "Fruit Veg", "price": 30, "image": "images/tomato.jpg" },
  { "name": "Onion", "main": "Food", "sub": "Vegetables", "type": "Bulb", "price": 35, "image": "images/onion.jpg" },
  { "name": "Spinach", "main": "Food", "sub": "Vegetables", "type": "Leafy", "price": 25, "image": "images/spinach.jpg" },
  { "name": "Milk", "main": "Food", "sub": "Dairy", "type": "Full Cream", "price": 60, "image": "images/milk.jpg" },
  { "name": "Yogurt", "main": "Food", "sub": "Dairy", "type": "Curd", "price": 80, "image": "images/yogurt.jpg" },
  { "name": "Cheese", "main": "Food", "sub": "Dairy", "type": "Cheddar", "price": 250, "image": "images/cheese.jpg" },
  { "name": "Butter", "main": "Food", "sub": "Dairy", "type": "Salted", "price": 180, "image": "images/butter.jpg" },
  { "name": "Eggs", "main": "Food", "sub": "Dairy", "type": "Farm Fresh", "price": 150, "image": "images/eggs.jpg" },
  { "name": "Bread", "main": "Food", "sub": "Bakery", "type": "Loaf", "price": 90, "image": "images/bread.jpg" },
  { "name": "Buns", "main": "Food", "sub": "Bakery", "type": "Burger", "price": 120, "image": "images/buns.jpg" },
  { "name": "Croissant", "main": "Food", "sub": "Bakery", "type": "Pastry", "price": 150, "image": "images/croissant.jpg" },
  { "name": "Muffin", "main": "Food", "sub": "Bakery", "type": "Cupcake", "price": 100, "image": "images/muffin.jpg" },
  { "name": "Cake", "main": "Food", "sub": "Bakery", "type": "Chocolate", "price": 500, "image": "images/cake.jpg" },
  { "name": "Tea", "main": "Food", "sub": "Beverages", "type": "Leaf", "price": 200, "image": "images/tea.jpg" },
  { "name": "Coffee", "main": "Food", "sub": "Beverages", "type": "Powder", "price": 250, "image": "images/coffee.jpg" },
  { "name": "Juice", "main": "Food", "sub": "Beverages", "type": "Fruit Juice", "price": 150, "image": "images/juice.jpg" },
  { "name": "Soda", "main": "Food", "sub": "Beverages", "type": "Soft Drink", "price": 100, "image": "images/soda.jpg" },
  { "name": "Water", "main": "Food", "sub": "Beverages", "type": "Mineral", "price": 50, "image": "images/water.jpg" },
  { "name": "Biscuits", "main": "Food", "sub": "Snacks", "type": "Sweet", "price": 120, "image": "images/biscuits.jpg" },
  { "name": "Chips", "main": "Food", "sub": "Snacks", "type": "Salty", "price": 150, "image": "images/chips.jpg" },
  { "name": "Nuts", "main": "Food", "sub": "Snacks", "type": "Almonds", "price": 300, "image": "images/nuts.jpg" },
  { "name": "Chocolate", "main": "Food", "sub": "Snacks", "type": "Bar", "price": 250, "image": "images/chocolate.jpg" },
  { "name": "Ice Cream", "main": "Food", "sub": "Snacks", "type": "Vanilla", "price": 200, "image": "images/ice_cream.jpg" },
  { "name": "Soap", "main": "Food", "sub": "Household", "type": "Bath", "price": 80, "image": "images/soap.jpg" },
  { "name": "Detergent", "main": "Food", "sub": "Household", "type": "Powder", "price": 200, "image": "images/detergent.jpg" },
  { "name": "Shampoo", "main": "Food", "sub": "Household", "type": "Hair", "price": 250, "image": "images/shampoo.jpg" },
  { "name": "Toothpaste", "main": "Food", "sub": "Household", "type": "Oral Care", "price": 150, "image": "images/toothpaste.jpg" },
  { "name": "Tissue", "main": "Food", "sub": "Household", "type": "Paper", "price": 50, "image": "images/tissue.jpg" }
]